checker.py
link_checker-0.1.2.dist-info/DESCRIPTION.rst
link_checker-0.1.2.dist-info/METADATA
link_checker-0.1.2.dist-info/RECORD
link_checker-0.1.2.dist-info/WHEEL
link_checker-0.1.2.dist-info/entry_points.txt
link_checker-0.1.2.dist-info/metadata.json
link_checker-0.1.2.dist-info/top_level.txt
