Metadata-Version: 2.0
Name: link-checker
Version: 0.1.2
Summary: A simple link checker intended mostly for CI usage
Home-page: https://github.com/budziq/link-checker
Author: Michał Budzyński
Author-email: budziq@gmail.com
License: UNKNOWN
Keywords: links link-checker CI HTML
Platform: UNKNOWN
Classifier: Development Status :: 4 - Beta
Classifier: Intended Audience :: Developers
Classifier: Topic :: Software Development :: Build Tools
Classifier: License :: OSI Approved :: MIT License
Classifier: Programming Language :: Python :: 3
Classifier: Programming Language :: Python :: 3.4
Classifier: Programming Language :: Python :: 3.5
Classifier: Programming Language :: Python :: 3.6
Requires-Dist: beautifulsoup4 (>=4.6)
Requires-Dist: click (>=6.7)
Requires-Dist: requests (>=2.18)
